{
  "metadata": {
    "locale": "DEFAULT",
    "totalStrings": 10,
    "uniqueStrings": 10
  },
  "strings": {
    "briefings_1": {
      "category": "Briefing",
      "context": "Mission Name",
      "text": "Sample Training Mission"
    },
    "briefings_2": {
      "category": "Briefing",
      "context": "Description",
      "text": "This is a sample DCS World mission created for testing the Miz Editor application. The mission demonstrates text extraction capabilities."
    },
    "briefings_3": {
      "category": "Briefing",
      "context": "Blue Task",
      "text": "Blue coalition objective: Complete all training exercises and return to base safely."
    },
    "briefings_4": {
      "category": "Briefing",
      "context": "Red Task",
      "text": "Red coalition objective: Defend assigned airspace from enemy incursions."
    },
    "briefings_5": {
      "category": "Briefing",
      "context": "Neutral Task",
      "text": "Neutral forces: Observe and report only."
    },
    "triggers_6": {
      "category": "Trigger",
      "context": "Mission Start Message",
      "text": "Welcome to the training mission. All pilots report to your assigned aircraft."
    },
    "triggers_7": {
      "category": "Trigger",
      "context": "Objective Complete",
      "text": "Excellent work! All objectives have been completed. Return to base."
    },
    "triggers_8": {
      "category": "Trigger",
      "context": "Warning Message",
      "text": "Warning: Enemy aircraft detected. All fighters scramble immediately."
    },
    "radio_9": {
      "category": "Radio",
      "context": "Radio Call 1",
      "text": "Overlord, Eagle Flight checking in, on station at Angels 25."
    },
    "radio_10": {
      "category": "Radio",
      "context": "Radio Call 2",
      "text": "Eagle Flight, Overlord, copy. Maintain CAP pattern and await further instructions."
    }
  }
}